meeting_roles/__init__.py
meeting_roles/__main__.py
meeting_roles/app.py
meeting_roles/config.ini
meeting_roles/meeting_manager.py
meeting_roles/run.py
meeting_roles/static/script.js
meeting_roles/static/style.css
meeting_roles/templates/error.html
meeting_roles/templates/help.html
meeting_roles/templates/home.html
meeting_roles/templates/update_person_form.html
tests/__init__.py
tests/test_meeting_manager.db
tests/test_meeting_manager.py
meeting_roles-0.1.0.dist-info/LICENSE
meeting_roles-0.1.0.dist-info/METADATA
meeting_roles-0.1.0.dist-info/WHEEL
meeting_roles-0.1.0.dist-info/entry_points.txt
meeting_roles-0.1.0.dist-info/top_level.txt
meeting_roles-0.1.0.dist-info/RECORD
