Metadata-Version: 2.1
Name: meeting-roles
Version: 0.1.0
Summary: A FastAPI web app to manage meeting roles
Home-page: https://git.coopdevs.org/coopdevs/tooling/meeting-roles-manager
Author: Coopdevs
Author-email: pelayo.garcia@coopdevs.org
Classifier: Development Status :: 3 - Alpha
Classifier: Intended Audience :: Developers
Classifier: License :: OSI Approved :: GNU Affero General Public License v3
Classifier: Programming Language :: Python :: 3
Classifier: Programming Language :: Python :: 3.8
Classifier: Programming Language :: Python :: 3.9
Classifier: Programming Language :: Python :: 3.10
License-File: LICENSE
Requires-Dist: fastapi
Requires-Dist: sqlite3
Requires-Dist: aiofiles
Requires-Dist: python-multipart
